src/debounce.v
`default_nettype none
`timescale 1ns/1ns
module debounce (
    input wire clk,
    input wire reset,
    input wire button,
    output reg debounced
);

reg [7:0] shift_reg;
reg eq_FF, eq_00;
wire en;
wire D;

always @(posedge clk) begin
    if (reset) begin
        shift_reg <= 8'b00000000;
    end else begin
        shift_reg = (shift_reg << 1) | button;

        if (shift_reg == 8'b11111111) begin
            eq_FF <= 1'b1;
            eq_00 <= 1'b0;
        end else if (shift_reg == 8'b00000000)begin
            eq_FF <=1'b0;
            eq_00 <=1'b1;
        end
    end
    
end
assign en = eq_FF | eq_00;
assign D = eq_FF ? 1'b1 : 1'b0;


always @(posedge clk ) begin
    if(reset)begin
        debounced <= 1'b0;
    end else if(en == 1'b1) begin
        debounced <= D;
    end 
end

endmodule

debounce.vcd
$date
	Mon Jun 24 19:23:56 2024
$end
$version
	Icarus Verilog
$end
$timescale
	1ns
$end
$scope module debounce $end
$var wire 1 ! button $end
$var wire 1 " clk $end
$var wire 1 # en $end
$var wire 1 $ reset $end
$var wire 1 % D $end
$var reg 1 & debounced $end
$var reg 1 ' eq_00 $end
$var reg 1 ( eq_FF $end
$var reg 8 ) shift_reg [7:0] $end
$upscope $end
$enddefinitions $end
$comment Show the parameter values. $end
$dumpall
$end
#0
$dumpvars
b0 )
x(
x'
0&
x%
1$
x#
1"
0!
$end
#5000
0"
#10000
1"
#15000
0"
#20000
1"
#25000
0"
#30000
1"
#35000
0"
#40000
0$
1"
#45000
0"
#50000
0%
1#
1'
0(
1"
#55000
0"
#60000
1"
#65000
0"
#70000
1"
#75000
0"
#80000
1"
#85000
0"
#90000
1"
#95000
0"
#100000
1!
1"
#105000
0"
#110000
0!
b1 )
1"
#115000
0"
#120000
b10 )
1"
#125000
0"
#130000
b100 )
1"
#135000
0"
#140000
1!
b1000 )
1"
#145000
0"
#150000
b10001 )
1"
#155000
0"
#160000
b100011 )
1"
#165000
0"
#170000
b1000111 )
1"
#175000
0"
#180000
b10001111 )
1"
#185000
0"
#190000
b11111 )
1"
#195000
0"
#200000
b111111 )
1"
#205000
0"
#210000
b1111111 )
1"
#215000
0"
#220000
1%
0'
1(
b11111111 )
1"
#225000
0"
#230000
1&
1"
#235000
0"
#240000
0!
1"
#245000
0"
#250000
1!
b11111110 )
1"
#255000
0"
#260000
0!
b11111101 )
1"
#265000
0"
#270000
1!
b11111010 )
1"
#275000
0"
#280000
b11110101 )
1"
#285000
0"
#290000
0!
b11101011 )
1"
#295000
0"
#300000
b11010110 )
1"
#305000
0"
#310000
b10101100 )
1"
#315000
0"
#320000
b1011000 )
1"
#325000
0"
#330000
b10110000 )
1"
#335000
0"
#340000
b1100000 )
1"
#345000
0"
#350000
b11000000 )
1"
#355000
0"
#360000
b10000000 )
1"
#365000
0"
#370000
0%
1'
0(
b0 )
1"
#375000
0"
#380000
0&
1"
#385000
0"
#390000
1"
#395000
0"
#400000
1!
1"
#405000
0"
#410000
b1 )
1"
#415000
0"
#420000
0!
b11 )
1"
#425000
0"
#430000
b110 )
1"
#435000
0"
#440000
1!
b1100 )
1"
#445000
0"
#450000
b11001 )
1"
#455000
0"
#460000
b110011 )
1"
#465000
0"
#470000
b1100111 )
1"
#475000
0"
#480000
b11001111 )
1"
#485000
0"
#490000
b10011111 )
1"
#495000
0"
#500000
b111111 )
1"
#505000
0"
#510000
b1111111 )
1"
#515000
0"
#520000
1%
0'
1(
b11111111 )
1"
#525000
0"
#530000
1&
1"
#535000
0"
#540000
1"
#545000
0"
#550000
0!
1"
#555000
0"
#560000
1!
b11111110 )
1"
#565000
0"
#570000
0!
b11111101 )
1"
#575000
0"
#580000
1!
b11111010 )
1"
#585000
0"
#590000
0!
b11110101 )
1"
#595000
0"
#600000
b11101010 )
1"
#605000
0"
#610000
b11010100 )
1"
#615000
0"
#620000
b10101000 )
1"
#625000
0"
#630000
b1010000 )
1"
#635000
0"
#640000
b10100000 )
1"
#645000
0"
#650000
b1000000 )
1"
#655000
0"
#660000
b10000000 )
1"
#665000
0"
#670000
0%
1'
0(
b0 )
1"
#675000
0"
#680000
0&
1"
#685000
0"
#690000
1"
#695000
0"
#700000
1"
#705000
0"
#710000
1"
#715000
0"
#720000
1"
#725000
0"
#730000
1"
#735000
0"
#740000
1!
1"
#745000
0"
#750000
b1 )
1"
#755000
0"
#760000
b11 )
1"
#765000
0"
#770000
b111 )
1"
#775000
0"
#780000
b1111 )
1"
#785000
0"
#790000
b11111 )
1"
#795000
0"
#800000
b111111 )
1"
#805000
0"
#810000
b1111111 )
1"
#815000
0"
#820000
1%
0'
1(
b11111111 )
1"
#825000
0"
#830000
1&
1"
#835000
0"
#840000
1"
#845000
0"
#850000
0!
1"
#855000
0"
#860000
1!
b11111110 )
1"
#865000
0"
#870000
0!
b11111101 )
1"
#875000
0"
#880000
b11111010 )
1"
#885000
0"
#890000
b11110100 )
1"
#895000
0"
#900000
b11101000 )
1"
#905000
0"
#910000
b11010000 )
1"
#915000
0"
#920000
b10100000 )
1"
#925000
0"
#930000
b1000000 )
1"
#935000
0"
#940000
b10000000 )
1"
#945000
0"
#950000
0%
1'
0(
b0 )
1"
#955000
0"
#960000
0&
1"
#965000
0"
#970000
1"
#975000
0"
#980000
1"
#985000
0"
#990000
1!
1"
#995000
0"
#1000000
0!
b1 )
1"
#1005000
0"
#1010000
b10 )
1"
#1015000
0"
#1020000
b100 )
1"
#1025000
0"
#1030000
1!
b1000 )
1"
#1035000
0"
#1040000
b10001 )
1"
#1045000
0"
#1050000
b100011 )
1"
#1055000
0"
#1060000
b1000111 )
1"
#1065000
0"
#1070000
b10001111 )
1"
#1075000
0"
#1080000
b11111 )
1"
#1085000
0"
#1090000
b111111 )
1"
#1095000
0"
#1100000
b1111111 )
1"
#1105000
0"
#1110000
1%
0'
1(
b11111111 )
1"
#1115000
0"
#1120000
1&
1"
#1125000
0"
#1130000
1"
#1135000
0"
#1140000
1"
#1145000
0"
#1150000
1"
#1155000
0"
#1160000
1"
#1165000
0"
#1170000
1"
#1175000
0"
#1180000
1"
#1185000
0"
#1190000
0!
1"
#1195000
0"
#1200000
b11111110 )
1"
#1205000
0"
#1210000
b11111100 )
1"
#1215000
0"
#1220000
b11111000 )
1"
#1225000
0"
#1230000
b11110000 )
1"
#1235000
0"
#1240000
b11100000 )
1"
#1245000
0"
#1250000
b11000000 )
1"
#1255000
0"
#1260000
b10000000 )
1"
#1265000
0"
#1270000
0%
1'
0(
b0 )
1"
#1275000
0"
#1280000
0&
1"
#1285000
0"
#1290000
1!
1"
#1295000
0"
#1300000
0!
b1 )
1"
#1305000
0"
#1310000
1!
b10 )
1"
#1315000
0"
#1320000
0!
b101 )
1"
#1325000
0"
#1330000
1!
b1010 )
1"
#1335000
0"
#1340000
b10101 )
1"
#1345000
0"
#1350000
b101011 )
1"
#1355000
0"
#1360000
b1010111 )
1"
#1365000
0"
#1370000
b10101111 )
1"
#1375000
0"
#1380000
b1011111 )
1"
#1385000
0"
#1390000
b10111111 )
1"
#1395000
0"
#1400000
b1111111 )
1"
#1405000
0"
#1410000
1%
0'
1(
b11111111 )
1"
#1415000
0"
#1420000
1&
1"
#1425000
0"
#1430000
1"
#1435000
0"
#1440000
0!
1"
#1445000
0"
#1450000
1!
b11111110 )
1"
#1455000
0"
#1460000
b11111101 )
1"
#1465000
0"
#1470000
0!
b11111011 )
1"
#1475000
0"
#1480000
1!
b11110110 )
1"
#1485000
0"
#1490000
0!
b11101101 )
1"
#1495000
0"
#1500000
b11011010 )
1"
#1505000
0"
#1510000
b10110100 )
1"
#1515000
0"
#1520000
b1101000 )
1"
#1525000
0"
#1530000
b11010000 )
1"
#1535000
0"
#1540000
b10100000 )
1"
#1545000
0"
#1550000
b1000000 )
1"
#1555000
0"
#1560000
b10000000 )
1"
#1565000
0"
#1570000
0%
1'
0(
b0 )
1"
#1575000
0"
#1580000
0&
1"
#1585000
0"
#1590000
1!
1"
#1595000
0"
#1600000
b1 )
1"
#1605000
0"
#1610000
b11 )
1"
#1615000
0"
#1620000
0!
b111 )
1"
#1625000
0"
#1630000
b1110 )
1"
#1635000
0"
#1640000
1!
b11100 )
1"
#1645000
0"
#1650000
b111001 )
1"
#1655000
0"
#1660000
b1110011 )
1"
#1665000
0"
#1670000
b11100111 )
1"
#1675000
0"
#1680000
b11001111 )
1"
#1685000
0"
#1690000
b10011111 )
1"
#1695000
0"
#1700000
b111111 )
1"
#1705000
0"
#1710000
b1111111 )
1"
#1715000
0"
#1720000
1%
0'
1(
b11111111 )
1"
#1725000
0"
#1730000
1&
1"
#1735000
0"
#1740000
1"
#1745000
0"
#1750000
1"
#1755000
0"
#1760000
1"
#1765000
0"
#1770000
0!
1"
#1775000
0"
#1780000
b11111110 )
1"
#1785000
0"
#1790000
b11111100 )
1"
#1795000
0"
#1800000
b11111000 )
1"
#1805000
0"
#1810000
b11110000 )
1"
#1815000
0"
#1820000
b11100000 )
1"
#1825000
0"
#1830000
b11000000 )
1"
#1835000
0"
#1840000
b10000000 )
1"
#1845000
0"
#1850000
0%
1'
0(
b0 )
1"
#1855000
0"
#1860000
0&
1"
#1865000
0"
#1870000
1"
#1875000
0"
#1880000
1"
#1885000
0"
#1890000
1"
#1895000
0"
#1900000
1!
1"
#1905000
0"
#1910000
0!
b1 )
1"
#1915000
0"
#1920000
b10 )
1"
#1925000
0"
#1930000
1!
b100 )
1"
#1935000
0"
#1940000
b1001 )
1"
#1945000
0"
#1950000
b10011 )
1"
#1955000
0"
#1960000
b100111 )
1"
#1965000
0"
#1970000
b1001111 )
1"
#1975000
0"
#1980000
b10011111 )
1"
#1985000
0"
#1990000
b111111 )
1"
#1995000
0"
#2000000
b1111111 )
1"
#2005000
0"
#2010000
1%
0'
1(
b11111111 )
1"
#2015000
0"
#2020000
1&
1"
#2025000
0"
#2030000
1"
#2035000
0"
#2040000
1"
#2045000
0"
#2050000
1"
#2055000
0"
#2060000
0!
1"
#2065000
0"
#2070000
b11111110 )
1"
#2075000
0"
#2080000
1!
b11111100 )
1"
#2085000
0"
#2090000
0!
b11111001 )
1"
#2095000
0"
#2100000
b11110010 )
1"
#2105000
0"
#2110000
b11100100 )
1"
#2115000
0"
#2120000
b11001000 )
1"
#2125000
0"
#2130000
b10010000 )
1"
#2135000
0"
#2140000
b100000 )
1"
#2145000
0"
#2150000
b1000000 )
1"
#2155000
0"
#2160000
b10000000 )
1"
#2165000
0"
#2170000
0%
1'
0(
b0 )
1"
#2175000
0"
#2180000
0&
1"
#2185000
0"
#2190000
1!
1"
#2195000
0"
#2200000
0!
b1 )
1"
#2205000
0"
#2210000
1!
b10 )
1"
#2215000
0"
#2220000
0!
b101 )
1"
#2225000
0"
#2230000
b1010 )
1"
#2235000
0"
#2240000
1!
b10100 )
1"
#2245000
0"
#2250000
b101001 )
1"
#2255000
0"
#2260000
b1010011 )
1"
#2265000
0"
#2270000
b10100111 )
1"
#2275000
0"
#2280000
b1001111 )
1"
#2285000
0"
#2290000
b10011111 )
1"
#2295000
0"
#2300000
b111111 )
1"
#2305000
0"
#2310000
b1111111 )
1"
#2315000
0"
#2320000
1%
0'
1(
b11111111 )
1"
#2325000
0"
#2330000
1&
1"
#2335000
0"
#2340000
0!
1"
#2345000
0"
#2350000
b11111110 )
1"
#2355000
0"
#2360000
b11111100 )
1"
#2365000
0"
#2370000
b11111000 )
1"
#2375000
0"
#2380000
b11110000 )
1"
#2385000
0"
#2390000
b11100000 )
1"
#2395000
0"
#2400000
b11000000 )
1"
#2405000
0"
#2410000
b10000000 )
1"
#2415000
0"
#2420000
0%
1'
0(
b0 )
1"
#2425000
0"
#2430000
0&
1"
#2435000
0"
#2440000
1"
#2445000
0"
#2450000
1"
#2455000
0"
#2460000
1"
#2465000
0"
#2470000
1"
#2475000
0"
#2480000
1"
#2485000
0"
#2490000
1!
1"
#2495000
0"
#2500000
0!
b1 )
1"
#2505000
0"
#2510000
1!
b10 )
1"
#2515000
0"
#2520000
0!
b101 )
1"
#2525000
0"
#2530000
b1010 )
1"
#2535000
0"
#2540000
1!
b10100 )
1"
#2545000
0"
#2550000
b101001 )
1"
#2555000
0"
#2560000
b1010011 )
1"
#2565000
0"
#2570000
b10100111 )
1"
#2575000
0"
#2580000
b1001111 )
1"
#2585000
0"
#2590000
b10011111 )
1"
#2595000
0"
#2600000
b111111 )
1"
#2605000
0"
#2610000
b1111111 )
1"
#2615000
0"
#2620000
1%
0'
1(
b11111111 )
1"
#2625000
0"
#2630000
1&
1"
#2635000
0"
#2640000
0!
1"
#2645000
0"
#2650000
1!
b11111110 )
1"
#2655000
0"
#2660000
0!
b11111101 )
1"
#2665000
0"
#2670000
1!
b11111010 )
1"
#2675000
0"
#2680000
b11110101 )
1"
#2685000
0"
#2690000
0!
b11101011 )
1"
#2695000
0"
#2700000
b11010110 )
1"
#2705000
0"
#2710000
b10101100 )
1"
#2715000
0"
#2720000
b1011000 )
1"
#2725000
0"
#2730000
b10110000 )
1"
#2735000
0"
#2740000
b1100000 )
1"
#2745000
0"
#2750000
b11000000 )
1"
#2755000
0"
#2760000
b10000000 )
1"
#2765000
0"
#2770000
0%
1'
0(
b0 )
1"
#2775000
0"
#2780000
0&
1"
#2785000
0"
#2790000
1"
#2795000
0"
#2800000
1!
1"
#2805000
0"
#2810000
0!
b1 )
1"
#2815000
0"
#2820000
1!
b10 )
1"
#2825000
0"
#2830000
b101 )
1"
#2835000
0"
#2840000
b1011 )
1"
#2845000
0"
#2850000
b10111 )
1"
#2855000
0"
#2860000
b101111 )
1"
#2865000
0"
#2870000
b1011111 )
1"
#2875000
0"
#2880000
b10111111 )
1"
#2885000
0"
#2890000
b1111111 )
1"
#2895000
0"
#2900000
1%
0'
1(
b11111111 )
1"
#2905000
0"
#2910000
1&
1"
#2915000
0"
#2920000
1"
#2925000
0"
#2930000
1"
#2935000
0"
#2940000
0!
1"
#2945000
0"
#2950000
1!
b11111110 )
1"
#2955000
0"
#2960000
b11111101 )
1"
#2965000
0"
#2970000
0!
b11111011 )
1"
#2975000
0"
#2980000
1!
b11110110 )
1"
#2985000
0"
#2990000
0!
b11101101 )
1"
#2995000
0"
#3000000
b11011010 )
1"
#3005000
0"
#3010000
b10110100 )
1"
#3015000
0"
#3020000
b1101000 )
1"
#3025000
0"
#3030000
b11010000 )
1"
#3035000
0"
#3040000
b10100000 )
1"
#3045000
0"
#3050000
b1000000 )
1"
#3055000
0"
#3060000
b10000000 )
1"
#3065000
0"
#3070000
0%
1'
0(
b0 )
1"
#3075000
0"
#3080000
0&
1"
