src/pwm.v
`default_nettype none // do not optimize
`timescale 1ns/1ns // simulation 

module pwm (
    input wire clk,
    input wire reset,
    output wire out,
    input wire [7:0] level
    );

    reg [7:0] count;
    reg out_reg;
    localparam MAX_COUNT = 255; //8 bit

    always @(posedge clk) begin
        if(reset) 
        begin // reset active high
            count <= 8'b00000000;
            out_reg <= 1'b0;
        end
        else
        begin
            if(count == MAX_COUNT) 
            begin
                count <= 8'b00000000; // reset count when reached max
            end
            else 
            begin
                count <= count + 1'b1; // increment counter

                if((level == 8'b00000000) || (level == 8'b11111111)) begin
                     if (count < level) //minus 1 as out_reg is a register and will have update delay of 1 clock cycle
                        out_reg <= 1'b1;
                    else
                        out_reg <= 1'b0;
                end else begin
                    if (count < level-1'b1) //minus 1 as out_reg is a register and will have update delay of 1 clock cycle
                        out_reg <= 1'b1;
                    else
                        out_reg <= 1'b0;
                end
                
                
               
                // if (count < level-1'b1) //minus 1 as out_reg is a register and will have update delay of 1 clock cycle
                // if (count < level-1'b1) //minus 1 as out_reg is a register and will have update delay of 1 clock cycle
                //     out_reg <= 1'b1;
                // else
                //     out_reg <= 1'b0;
            end
        end
    end

    assign out = out_reg;

endmodule

pwm.vcd
$date
	Mon Jun 24 19:23:57 2024
$end
$version
	Icarus Verilog
$end
$timescale
	1ns
$end
$scope module pwm $end
$var wire 1 ! clk $end
$var wire 8 " level [7:0] $end
$var wire 1 # out $end
$var wire 1 $ reset $end
$var parameter 32 % MAX_COUNT $end
$var reg 8 & count [7:0] $end
$var reg 1 ' out_reg $end
$upscope $end
$enddefinitions $end
$comment Show the parameter values. $end
$dumpall
b11111111 %
$end
#0
$dumpvars
0'
b0 &
1$
0#
b1010 "
1!
$end
#5000
0!
#10000
1!
#15000
0!
#20000
1!
#25000
0!
#30000
1!
#35000
0!
#40000
0$
1!
#45000
0!
#50000
1#
1'
b1 &
1!
#55000
0!
#60000
b10 &
1!
#65000
0!
#70000
b11 &
1!
#75000
0!
#80000
b100 &
1!
#85000
0!
#90000
b101 &
1!
#95000
0!
#100000
b110 &
1!
#105000
0!
#110000
b111 &
1!
#115000
0!
#120000
b1000 &
1!
#125000
0!
#130000
b1001 &
1!
#135000
0!
#140000
0#
0'
b1010 &
1!
#145000
0!
#150000
b1011 &
1!
#155000
0!
#160000
b1100 &
1!
#165000
0!
#170000
b1101 &
1!
#175000
0!
#180000
b1110 &
1!
#185000
0!
#190000
b1111 &
1!
#195000
0!
#200000
b10000 &
1!
#205000
0!
#210000
b10001 &
1!
#215000
0!
#220000
b10010 &
1!
#225000
0!
#230000
b10011 &
1!
#235000
0!
#240000
b10100 &
1!
#245000
0!
#250000
b10101 &
1!
#255000
0!
#260000
b10110 &
1!
#265000
0!
#270000
b10111 &
1!
#275000
0!
#280000
b11000 &
1!
#285000
0!
#290000
b11001 &
1!
#295000
0!
#300000
b11010 &
1!
#305000
0!
#310000
b11011 &
1!
#315000
0!
#320000
b11100 &
1!
#325000
0!
#330000
b11101 &
1!
#335000
0!
#340000
b11110 &
1!
#345000
0!
#350000
b11111 &
1!
#355000
0!
#360000
b100000 &
1!
#365000
0!
#370000
b100001 &
1!
#375000
0!
#380000
b100010 &
1!
#385000
0!
#390000
b100011 &
1!
#395000
0!
#400000
b100100 &
1!
#405000
0!
#410000
b100101 &
1!
#415000
0!
#420000
b100110 &
1!
#425000
0!
#430000
b100111 &
1!
#435000
0!
#440000
b101000 &
1!
#445000
0!
#450000
b101001 &
1!
#455000
0!
#460000
b101010 &
1!
#465000
0!
#470000
b101011 &
1!
#475000
0!
#480000
b101100 &
1!
#485000
0!
#490000
b101101 &
1!
#495000
0!
#500000
b101110 &
1!
#505000
0!
#510000
b101111 &
1!
#515000
0!
#520000
b110000 &
1!
#525000
0!
#530000
b110001 &
1!
#535000
0!
#540000
b110010 &
1!
#545000
0!
#550000
b110011 &
1!
#555000
0!
#560000
b110100 &
1!
#565000
0!
#570000
b110101 &
1!
#575000
0!
#580000
b110110 &
1!
#585000
0!
#590000
b110111 &
1!
#595000
0!
#600000
b111000 &
1!
#605000
0!
#610000
b111001 &
1!
#615000
0!
#620000
b111010 &
1!
#625000
0!
#630000
b111011 &
1!
#635000
0!
#640000
b111100 &
1!
#645000
0!
#650000
b111101 &
1!
#655000
0!
#660000
b111110 &
1!
#665000
0!
#670000
b111111 &
1!
#675000
0!
#680000
b1000000 &
1!
#685000
0!
#690000
b1000001 &
1!
#695000
0!
#700000
b1000010 &
1!
#705000
0!
#710000
b1000011 &
1!
#715000
0!
#720000
b1000100 &
1!
#725000
0!
#730000
b1000101 &
1!
#735000
0!
#740000
b1000110 &
1!
#745000
0!
#750000
b1000111 &
1!
#755000
0!
#760000
b1001000 &
1!
#765000
0!
#770000
b1001001 &
1!
#775000
0!
#780000
b1001010 &
1!
#785000
0!
#790000
b1001011 &
1!
#795000
0!
#800000
b1001100 &
1!
#805000
0!
#810000
b1001101 &
1!
#815000
0!
#820000
b1001110 &
1!
#825000
0!
#830000
b1001111 &
1!
#835000
0!
#840000
b1010000 &
1!
#845000
0!
#850000
b1010001 &
1!
#855000
0!
#860000
b1010010 &
1!
#865000
0!
#870000
b1010011 &
1!
#875000
0!
#880000
b1010100 &
1!
#885000
0!
#890000
b1010101 &
1!
#895000
0!
#900000
b1010110 &
1!
#905000
0!
#910000
b1010111 &
1!
#915000
0!
#920000
b1011000 &
1!
#925000
0!
#930000
b1011001 &
1!
#935000
0!
#940000
b1011010 &
1!
#945000
0!
#950000
b1011011 &
1!
#955000
0!
#960000
b1011100 &
1!
#965000
0!
#970000
b1011101 &
1!
#975000
0!
#980000
b1011110 &
1!
#985000
0!
#990000
b1011111 &
1!
#995000
0!
#1000000
b1100000 &
1!
#1005000
0!
#1010000
b1100001 &
1!
#1015000
0!
#1020000
b1100010 &
1!
#1025000
0!
#1030000
b1100011 &
1!
#1035000
0!
#1040000
b1100100 &
1!
#1045000
0!
#1050000
b1100101 &
1!
#1055000
0!
#1060000
b1100110 &
1!
#1065000
0!
#1070000
b1100111 &
1!
#1075000
0!
#1080000
b1101000 &
1!
#1085000
0!
#1090000
b1101001 &
1!
#1095000
0!
#1100000
b1101010 &
1!
#1105000
0!
#1110000
b1101011 &
1!
#1115000
0!
#1120000
b1101100 &
1!
#1125000
0!
#1130000
b1101101 &
1!
#1135000
0!
#1140000
b1101110 &
1!
#1145000
0!
#1150000
b1101111 &
1!
#1155000
0!
#1160000
b1110000 &
1!
#1165000
0!
#1170000
b1110001 &
1!
#1175000
0!
#1180000
b1110010 &
1!
#1185000
0!
#1190000
b1110011 &
1!
#1195000
0!
#1200000
b1110100 &
1!
#1205000
0!
#1210000
b1110101 &
1!
#1215000
0!
#1220000
b1110110 &
1!
#1225000
0!
#1230000
b1110111 &
1!
#1235000
0!
#1240000
b1111000 &
1!
#1245000
0!
#1250000
b1111001 &
1!
#1255000
0!
#1260000
b1111010 &
1!
#1265000
0!
#1270000
b1111011 &
1!
#1275000
0!
#1280000
b1111100 &
1!
#1285000
0!
#1290000
b1111101 &
1!
#1295000
0!
#1300000
b1111110 &
1!
#1305000
0!
#1310000
b1111111 &
1!
#1315000
0!
#1320000
b10000000 &
1!
#1325000
0!
#1330000
b10000001 &
1!
#1335000
0!
#1340000
b10000010 &
1!
#1345000
0!
#1350000
b10000011 &
1!
#1355000
0!
#1360000
b10000100 &
1!
#1365000
0!
#1370000
b10000101 &
1!
#1375000
0!
#1380000
b10000110 &
1!
#1385000
0!
#1390000
b10000111 &
1!
#1395000
0!
#1400000
b10001000 &
1!
#1405000
0!
#1410000
b10001001 &
1!
#1415000
0!
#1420000
b10001010 &
1!
#1425000
0!
#1430000
b10001011 &
1!
#1435000
0!
#1440000
b10001100 &
1!
#1445000
0!
#1450000
b10001101 &
1!
#1455000
0!
#1460000
b10001110 &
1!
#1465000
0!
#1470000
b10001111 &
1!
#1475000
0!
#1480000
b10010000 &
1!
#1485000
0!
#1490000
b10010001 &
1!
#1495000
0!
#1500000
b10010010 &
1!
#1505000
0!
#1510000
b10010011 &
1!
#1515000
0!
#1520000
b10010100 &
1!
#1525000
0!
#1530000
b10010101 &
1!
#1535000
0!
#1540000
b10010110 &
1!
#1545000
0!
#1550000
b10010111 &
1!
#1555000
0!
#1560000
b10011000 &
1!
#1565000
0!
#1570000
b10011001 &
1!
#1575000
0!
#1580000
b10011010 &
1!
#1585000
0!
#1590000
b10011011 &
1!
#1595000
0!
#1600000
b10011100 &
1!
#1605000
0!
#1610000
b10011101 &
1!
#1615000
0!
#1620000
b10011110 &
1!
#1625000
0!
#1630000
b10011111 &
1!
#1635000
0!
#1640000
b10100000 &
1!
#1645000
0!
#1650000
b10100001 &
1!
#1655000
0!
#1660000
b10100010 &
1!
#1665000
0!
#1670000
b10100011 &
1!
#1675000
0!
#1680000
b10100100 &
1!
#1685000
0!
#1690000
b10100101 &
1!
#1695000
0!
#1700000
b10100110 &
1!
#1705000
0!
#1710000
b10100111 &
1!
#1715000
0!
#1720000
b10101000 &
1!
#1725000
0!
#1730000
b10101001 &
1!
#1735000
0!
#1740000
b10101010 &
1!
#1745000
0!
#1750000
b10101011 &
1!
#1755000
0!
#1760000
b10101100 &
1!
#1765000
0!
#1770000
b10101101 &
1!
#1775000
0!
#1780000
b10101110 &
1!
#1785000
0!
#1790000
b10101111 &
1!
#1795000
0!
#1800000
b10110000 &
1!
#1805000
0!
#1810000
b10110001 &
1!
#1815000
0!
#1820000
b10110010 &
1!
#1825000
0!
#1830000
b10110011 &
1!
#1835000
0!
#1840000
b10110100 &
1!
#1845000
0!
#1850000
b10110101 &
1!
#1855000
0!
#1860000
b10110110 &
1!
#1865000
0!
#1870000
b10110111 &
1!
#1875000
0!
#1880000
b10111000 &
1!
#1885000
0!
#1890000
b10111001 &
1!
#1895000
0!
#1900000
b10111010 &
1!
#1905000
0!
#1910000
b10111011 &
1!
#1915000
0!
#1920000
b10111100 &
1!
#1925000
0!
#1930000
b10111101 &
1!
#1935000
0!
#1940000
b10111110 &
1!
#1945000
0!
#1950000
b10111111 &
1!
#1955000
0!
#1960000
b11000000 &
1!
#1965000
0!
#1970000
b11000001 &
1!
#1975000
0!
#1980000
b11000010 &
1!
#1985000
0!
#1990000
b11000011 &
1!
#1995000
0!
#2000000
b11000100 &
1!
#2005000
0!
#2010000
b11000101 &
1!
#2015000
0!
#2020000
b11000110 &
1!
#2025000
0!
#2030000
b11000111 &
1!
#2035000
0!
#2040000
b11001000 &
1!
#2045000
0!
#2050000
b11001001 &
1!
#2055000
0!
#2060000
b11001010 &
1!
#2065000
0!
#2070000
b11001011 &
1!
#2075000
0!
#2080000
b11001100 &
1!
#2085000
0!
#2090000
b11001101 &
1!
#2095000
0!
#2100000
b11001110 &
1!
#2105000
0!
#2110000
b11001111 &
1!
#2115000
0!
#2120000
b11010000 &
1!
#2125000
0!
#2130000
b11010001 &
1!
#2135000
0!
#2140000
b11010010 &
1!
#2145000
0!
#2150000
b11010011 &
1!
#2155000
0!
#2160000
b11010100 &
1!
#2165000
0!
#2170000
b11010101 &
1!
#2175000
0!
#2180000
b11010110 &
1!
#2185000
0!
#2190000
b11010111 &
1!
#2195000
0!
#2200000
b11011000 &
1!
#2205000
0!
#2210000
b11011001 &
1!
#2215000
0!
#2220000
b11011010 &
1!
#2225000
0!
#2230000
b11011011 &
1!
#2235000
0!
#2240000
b11011100 &
1!
#2245000
0!
#2250000
b11011101 &
1!
#2255000
0!
#2260000
b11011110 &
1!
#2265000
0!
#2270000
b11011111 &
1!
#2275000
0!
#2280000
b11100000 &
1!
#2285000
0!
#2290000
b11100001 &
1!
#2295000
0!
#2300000
b11100010 &
1!
#2305000
0!
#2310000
b11100011 &
1!
#2315000
0!
#2320000
b11100100 &
1!
#2325000
0!
#2330000
b11100101 &
1!
#2335000
0!
#2340000
b11100110 &
1!
#2345000
0!
#2350000
b11100111 &
1!
#2355000
0!
#2360000
b11101000 &
1!
#2365000
0!
#2370000
b11101001 &
1!
#2375000
0!
#2380000
b11101010 &
1!
#2385000
0!
#2390000
b11101011 &
1!
#2395000
0!
#2400000
b11101100 &
1!
#2405000
0!
#2410000
b11101101 &
1!
#2415000
0!
#2420000
b11101110 &
1!
#2425000
0!
#2430000
b11101111 &
1!
#2435000
0!
#2440000
b11110000 &
1!
#2445000
0!
#2450000
b11110001 &
1!
#2455000
0!
#2460000
b11110010 &
1!
#2465000
0!
#2470000
b11110011 &
1!
#2475000
0!
#2480000
b11110100 &
1!
#2485000
0!
#2490000
b11110101 &
1!
#2495000
0!
#2500000
b11110110 &
1!
#2505000
0!
#2510000
b11110111 &
1!
#2515000
0!
#2520000
b11111000 &
1!
#2525000
0!
#2530000
b11111001 &
1!
#2535000
0!
#2540000
b11111010 &
1!
#2545000
0!
#2550000
b11111011 &
1!
#2555000
0!
#2560000
b11111100 &
1!
#2565000
0!
#2570000
b11111101 &
1!
#2575000
0!
#2580000
b11111110 &
1!
#2585000
0!
#2590000
1$
b11110 "
b11111111 &
1!
#2595000
0!
#2600000
b0 &
1!
#2605000
0!
#2610000
1!
#2615000
0!
#2620000
1!
#2625000
0!
#2630000
1!
#2635000
0!
#2640000
0$
1!
#2645000
0!
#2650000
1#
1'
b1 &
1!
#2655000
0!
#2660000
b10 &
1!
#2665000
0!
#2670000
b11 &
1!
#2675000
0!
#2680000
b100 &
1!
#2685000
0!
#2690000
b101 &
1!
#2695000
0!
#2700000
b110 &
1!
#2705000
0!
#2710000
b111 &
1!
#2715000
0!
#2720000
b1000 &
1!
#2725000
0!
#2730000
b1001 &
1!
#2735000
0!
#2740000
b1010 &
1!
#2745000
0!
#2750000
b1011 &
1!
#2755000
0!
#2760000
b1100 &
1!
#2765000
0!
#2770000
b1101 &
1!
#2775000
0!
#2780000
b1110 &
1!
#2785000
0!
#2790000
b1111 &
1!
#2795000
0!
#2800000
b10000 &
1!
#2805000
0!
#2810000
b10001 &
1!
#2815000
0!
#2820000
b10010 &
1!
#2825000
0!
#2830000
b10011 &
1!
#2835000
0!
#2840000
b10100 &
1!
#2845000
0!
#2850000
b10101 &
1!
#2855000
0!
#2860000
b10110 &
1!
#2865000
0!
#2870000
b10111 &
1!
#2875000
0!
#2880000
b11000 &
1!
#2885000
0!
#2890000
b11001 &
1!
#2895000
0!
#2900000
b11010 &
1!
#2905000
0!
#2910000
b11011 &
1!
#2915000
0!
#2920000
b11100 &
1!
#2925000
0!
#2930000
b11101 &
1!
#2935000
0!
#2940000
0#
0'
b11110 &
1!
#2945000
0!
#2950000
b11111 &
1!
#2955000
0!
#2960000
b100000 &
1!
#2965000
0!
#2970000
b100001 &
1!
#2975000
0!
#2980000
b100010 &
1!
#2985000
0!
#2990000
b100011 &
1!
#2995000
0!
#3000000
b100100 &
1!
#3005000
0!
#3010000
b100101 &
1!
#3015000
0!
#3020000
b100110 &
1!
#3025000
0!
#3030000
b100111 &
1!
#3035000
0!
#3040000
b101000 &
1!
#3045000
0!
#3050000
b101001 &
1!
#3055000
0!
#3060000
b101010 &
1!
#3065000
0!
#3070000
b101011 &
1!
#3075000
0!
#3080000
b101100 &
1!
#3085000
0!
#3090000
b101101 &
1!
#3095000
0!
#3100000
b101110 &
1!
#3105000
0!
#3110000
b101111 &
1!
#3115000
0!
#3120000
b110000 &
1!
#3125000
0!
#3130000
b110001 &
1!
#3135000
0!
#3140000
b110010 &
1!
#3145000
0!
#3150000
b110011 &
1!
#3155000
0!
#3160000
b110100 &
1!
#3165000
0!
#3170000
b110101 &
1!
#3175000
0!
#3180000
b110110 &
1!
#3185000
0!
#3190000
b110111 &
1!
#3195000
0!
#3200000
b111000 &
1!
#3205000
0!
#3210000
b111001 &
1!
#3215000
0!
#3220000
b111010 &
1!
#3225000
0!
#3230000
b111011 &
1!
#3235000
0!
#3240000
b111100 &
1!
#3245000
0!
#3250000
b111101 &
1!
#3255000
0!
#3260000
b111110 &
1!
#3265000
0!
#3270000
b111111 &
1!
#3275000
0!
#3280000
b1000000 &
1!
#3285000
0!
#3290000
b1000001 &
1!
#3295000
0!
#3300000
b1000010 &
1!
#3305000
0!
#3310000
b1000011 &
1!
#3315000
0!
#3320000
b1000100 &
1!
#3325000
0!
#3330000
b1000101 &
1!
#3335000
0!
#3340000
b1000110 &
1!
#3345000
0!
#3350000
b1000111 &
1!
#3355000
0!
#3360000
b1001000 &
1!
#3365000
0!
#3370000
b1001001 &
1!
#3375000
0!
#3380000
b1001010 &
1!
#3385000
0!
#3390000
b1001011 &
1!
#3395000
0!
#3400000
b1001100 &
1!
#3405000
0!
#3410000
b1001101 &
1!
#3415000
0!
#3420000
b1001110 &
1!
#3425000
0!
#3430000
b1001111 &
1!
#3435000
0!
#3440000
b1010000 &
1!
#3445000
0!
#3450000
b1010001 &
1!
#3455000
0!
#3460000
b1010010 &
1!
#3465000
0!
#3470000
b1010011 &
1!
#3475000
0!
#3480000
b1010100 &
1!
#3485000
0!
#3490000
b1010101 &
1!
#3495000
0!
#3500000
b1010110 &
1!
#3505000
0!
#3510000
b1010111 &
1!
#3515000
0!
#3520000
b1011000 &
1!
#3525000
0!
#3530000
b1011001 &
1!
#3535000
0!
#3540000
b1011010 &
1!
#3545000
0!
#3550000
b1011011 &
1!
#3555000
0!
#3560000
b1011100 &
1!
#3565000
0!
#3570000
b1011101 &
1!
#3575000
0!
#3580000
b1011110 &
1!
#3585000
0!
#3590000
b1011111 &
1!
#3595000
0!
#3600000
b1100000 &
1!
#3605000
0!
#3610000
b1100001 &
1!
#3615000
0!
#3620000
b1100010 &
1!
#3625000
0!
#3630000
b1100011 &
1!
#3635000
0!
#3640000
b1100100 &
1!
#3645000
0!
#3650000
b1100101 &
1!
#3655000
0!
#3660000
b1100110 &
1!
#3665000
0!
#3670000
b1100111 &
1!
#3675000
0!
#3680000
b1101000 &
1!
#3685000
0!
#3690000
b1101001 &
1!
#3695000
0!
#3700000
b1101010 &
1!
#3705000
0!
#3710000
b1101011 &
1!
#3715000
0!
#3720000
b1101100 &
1!
#3725000
0!
#3730000
b1101101 &
1!
#3735000
0!
#3740000
b1101110 &
1!
#3745000
0!
#3750000
b1101111 &
1!
#3755000
0!
#3760000
b1110000 &
1!
#3765000
0!
#3770000
b1110001 &
1!
#3775000
0!
#3780000
b1110010 &
1!
#3785000
0!
#3790000
b1110011 &
1!
#3795000
0!
#3800000
b1110100 &
1!
#3805000
0!
#3810000
b1110101 &
1!
#3815000
0!
#3820000
b1110110 &
1!
#3825000
0!
#3830000
b1110111 &
1!
#3835000
0!
#3840000
b1111000 &
1!
#3845000
0!
#3850000
b1111001 &
1!
#3855000
0!
#3860000
b1111010 &
1!
#3865000
0!
#3870000
b1111011 &
1!
#3875000
0!
#3880000
b1111100 &
1!
#3885000
0!
#3890000
b1111101 &
1!
#3895000
0!
#3900000
b1111110 &
1!
#3905000
0!
#3910000
b1111111 &
1!
#3915000
0!
#3920000
b10000000 &
1!
#3925000
0!
#3930000
b10000001 &
1!
#3935000
0!
#3940000
b10000010 &
1!
#3945000
0!
#3950000
b10000011 &
1!
#3955000
0!
#3960000
b10000100 &
1!
#3965000
0!
#3970000
b10000101 &
1!
#3975000
0!
#3980000
b10000110 &
1!
#3985000
0!
#3990000
b10000111 &
1!
#3995000
0!
#4000000
b10001000 &
1!
#4005000
0!
#4010000
b10001001 &
1!
#4015000
0!
#4020000
b10001010 &
1!
#4025000
0!
#4030000
b10001011 &
1!
#4035000
0!
#4040000
b10001100 &
1!
#4045000
0!
#4050000
b10001101 &
1!
#4055000
0!
#4060000
b10001110 &
1!
#4065000
0!
#4070000
b10001111 &
1!
#4075000
0!
#4080000
b10010000 &
1!
#4085000
0!
#4090000
b10010001 &
1!
#4095000
0!
#4100000
b10010010 &
1!
#4105000
0!
#4110000
b10010011 &
1!
#4115000
0!
#4120000
b10010100 &
1!
#4125000
0!
#4130000
b10010101 &
1!
#4135000
0!
#4140000
b10010110 &
1!
#4145000
0!
#4150000
b10010111 &
1!
#4155000
0!
#4160000
b10011000 &
1!
#4165000
0!
#4170000
b10011001 &
1!
#4175000
0!
#4180000
b10011010 &
1!
#4185000
0!
#4190000
b10011011 &
1!
#4195000
0!
#4200000
b10011100 &
1!
#4205000
0!
#4210000
b10011101 &
1!
#4215000
0!
#4220000
b10011110 &
1!
#4225000
0!
#4230000
b10011111 &
1!
#4235000
0!
#4240000
b10100000 &
1!
#4245000
0!
#4250000
b10100001 &
1!
#4255000
0!
#4260000
b10100010 &
1!
#4265000
0!
#4270000
b10100011 &
1!
#4275000
0!
#4280000
b10100100 &
1!
#4285000
0!
#4290000
b10100101 &
1!
#4295000
0!
#4300000
b10100110 &
1!
#4305000
0!
#4310000
b10100111 &
1!
#4315000
0!
#4320000
b10101000 &
1!
#4325000
0!
#4330000
b10101001 &
1!
#4335000
0!
#4340000
b10101010 &
1!
#4345000
0!
#4350000
b10101011 &
1!
#4355000
0!
#4360000
b10101100 &
1!
#4365000
0!
#4370000
b10101101 &
1!
#4375000
0!
#4380000
b10101110 &
1!
#4385000
0!
#4390000
b10101111 &
1!
#4395000
0!
#4400000
b10110000 &
1!
#4405000
0!
#4410000
b10110001 &
1!
#4415000
0!
#4420000
b10110010 &
1!
#4425000
0!
#4430000
b10110011 &
1!
#4435000
0!
#4440000
b10110100 &
1!
#4445000
0!
#4450000
b10110101 &
1!
#4455000
0!
#4460000
b10110110 &
1!
#4465000
0!
#4470000
b10110111 &
1!
#4475000
0!
#4480000
b10111000 &
1!
#4485000
0!
#4490000
b10111001 &
1!
#4495000
0!
#4500000
b10111010 &
1!
#4505000
0!
#4510000
b10111011 &
1!
#4515000
0!
#4520000
b10111100 &
1!
#4525000
0!
#4530000
b10111101 &
1!
#4535000
0!
#4540000
b10111110 &
1!
#4545000
0!
#4550000
b10111111 &
1!
#4555000
0!
#4560000
b11000000 &
1!
#4565000
0!
#4570000
b11000001 &
1!
#4575000
0!
#4580000
b11000010 &
1!
#4585000
0!
#4590000
b11000011 &
1!
#4595000
0!
#4600000
b11000100 &
1!
#4605000
0!
#4610000
b11000101 &
1!
#4615000
0!
#4620000
b11000110 &
1!
#4625000
0!
#4630000
b11000111 &
1!
#4635000
0!
#4640000
b11001000 &
1!
#4645000
0!
#4650000
b11001001 &
1!
#4655000
0!
#4660000
b11001010 &
1!
#4665000
0!
#4670000
b11001011 &
1!
#4675000
0!
#4680000
b11001100 &
1!
#4685000
0!
#4690000
b11001101 &
1!
#4695000
0!
#4700000
b11001110 &
1!
#4705000
0!
#4710000
b11001111 &
1!
#4715000
0!
#4720000
b11010000 &
1!
#4725000
0!
#4730000
b11010001 &
1!
#4735000
0!
#4740000
b11010010 &
1!
#4745000
0!
#4750000
b11010011 &
1!
#4755000
0!
#4760000
b11010100 &
1!
#4765000
0!
#4770000
b11010101 &
1!
#4775000
0!
#4780000
b11010110 &
1!
#4785000
0!
#4790000
b11010111 &
1!
#4795000
0!
#4800000
b11011000 &
1!
#4805000
0!
#4810000
b11011001 &
1!
#4815000
0!
#4820000
b11011010 &
1!
#4825000
0!
#4830000
b11011011 &
1!
#4835000
0!
#4840000
b11011100 &
1!
#4845000
0!
#4850000
b11011101 &
1!
#4855000
0!
#4860000
b11011110 &
1!
#4865000
0!
#4870000
b11011111 &
1!
#4875000
0!
#4880000
b11100000 &
1!
#4885000
0!
#4890000
b11100001 &
1!
#4895000
0!
#4900000
b11100010 &
1!
#4905000
0!
#4910000
b11100011 &
1!
#4915000
0!
#4920000
b11100100 &
1!
#4925000
0!
#4930000
b11100101 &
1!
#4935000
0!
#4940000
b11100110 &
1!
#4945000
0!
#4950000
b11100111 &
1!
#4955000
0!
#4960000
b11101000 &
1!
#4965000
0!
#4970000
b11101001 &
1!
#4975000
0!
#4980000
b11101010 &
1!
#4985000
0!
#4990000
b11101011 &
1!
#4995000
0!
#5000000
b11101100 &
1!
#5005000
0!
#5010000
b11101101 &
1!
#5015000
0!
#5020000
b11101110 &
1!
#5025000
0!
#5030000
b11101111 &
1!
#5035000
0!
#5040000
b11110000 &
1!
#5045000
0!
#5050000
b11110001 &
1!
#5055000
0!
#5060000
b11110010 &
1!
#5065000
0!
#5070000
b11110011 &
1!
#5075000
0!
#5080000
b11110100 &
1!
#5085000
0!
#5090000
b11110101 &
1!
#5095000
0!
#5100000
b11110110 &
1!
#5105000
0!
#5110000
b11110111 &
1!
#5115000
0!
#5120000
b11111000 &
1!
#5125000
0!
#5130000
b11111001 &
1!
#5135000
0!
#5140000
b11111010 &
1!
#5145000
0!
#5150000
b11111011 &
1!
#5155000
0!
#5160000
b11111100 &
1!
#5165000
0!
#5170000
b11111101 &
1!
#5175000
0!
#5180000
b11111110 &
1!
#5185000
0!
#5190000
1$
b110010 "
b11111111 &
1!
#5195000
0!
#5200000
b0 &
1!
#5205000
0!
#5210000
1!
#5215000
0!
#5220000
1!
#5225000
0!
#5230000
1!
#5235000
0!
#5240000
0$
1!
#5245000
0!
#5250000
1#
1'
b1 &
1!
#5255000
0!
#5260000
b10 &
1!
#5265000
0!
#5270000
b11 &
1!
#5275000
0!
#5280000
b100 &
1!
#5285000
0!
#5290000
b101 &
1!
#5295000
0!
#5300000
b110 &
1!
#5305000
0!
#5310000
b111 &
1!
#5315000
0!
#5320000
b1000 &
1!
#5325000
0!
#5330000
b1001 &
1!
#5335000
0!
#5340000
b1010 &
1!
#5345000
0!
#5350000
b1011 &
1!
#5355000
0!
#5360000
b1100 &
1!
#5365000
0!
#5370000
b1101 &
1!
#5375000
0!
#5380000
b1110 &
1!
#5385000
0!
#5390000
b1111 &
1!
#5395000
0!
#5400000
b10000 &
1!
#5405000
0!
#5410000
b10001 &
1!
#5415000
0!
#5420000
b10010 &
1!
#5425000
0!
#5430000
b10011 &
1!
#5435000
0!
#5440000
b10100 &
1!
#5445000
0!
#5450000
b10101 &
1!
#5455000
0!
#5460000
b10110 &
1!
#5465000
0!
#5470000
b10111 &
1!
#5475000
0!
#5480000
b11000 &
1!
#5485000
0!
#5490000
b11001 &
1!
#5495000
0!
#5500000
b11010 &
1!
#5505000
0!
#5510000
b11011 &
1!
#5515000
0!
#5520000
b11100 &
1!
#5525000
0!
#5530000
b11101 &
1!
#5535000
0!
#5540000
b11110 &
1!
#5545000
0!
#5550000
b11111 &
1!
#5555000
0!
#5560000
b100000 &
1!
#5565000
0!
#5570000
b100001 &
1!
#5575000
0!
#5580000
b100010 &
1!
#5585000
0!
#5590000
b100011 &
1!
#5595000
0!
#5600000
b100100 &
1!
#5605000
0!
#5610000
b100101 &
1!
#5615000
0!
#5620000
b100110 &
1!
#5625000
0!
#5630000
b100111 &
1!
#5635000
0!
#5640000
b101000 &
1!
#5645000
0!
#5650000
b101001 &
1!
#5655000
0!
#5660000
b101010 &
1!
#5665000
0!
#5670000
b101011 &
1!
#5675000
0!
#5680000
b101100 &
1!
#5685000
0!
#5690000
b101101 &
1!
#5695000
0!
#5700000
b101110 &
1!
#5705000
0!
#5710000
b101111 &
1!
#5715000
0!
#5720000
b110000 &
1!
#5725000
0!
#5730000
b110001 &
1!
#5735000
0!
#5740000
0#
0'
b110010 &
1!
#5745000
0!
#5750000
b110011 &
1!
#5755000
0!
#5760000
b110100 &
1!
#5765000
0!
#5770000
b110101 &
1!
#5775000
0!
#5780000
b110110 &
1!
#5785000
0!
#5790000
b110111 &
1!
#5795000
0!
#5800000
b111000 &
1!
#5805000
0!
#5810000
b111001 &
1!
#5815000
0!
#5820000
b111010 &
1!
#5825000
0!
#5830000
b111011 &
1!
#5835000
0!
#5840000
b111100 &
1!
#5845000
0!
#5850000
b111101 &
1!
#5855000
0!
#5860000
b111110 &
1!
#5865000
0!
#5870000
b111111 &
1!
#5875000
0!
#5880000
b1000000 &
1!
#5885000
0!
#5890000
b1000001 &
1!
#5895000
0!
#5900000
b1000010 &
1!
#5905000
0!
#5910000
b1000011 &
1!
#5915000
0!
#5920000
b1000100 &
1!
#5925000
0!
#5930000
b1000101 &
1!
#5935000
0!
#5940000
b1000110 &
1!
#5945000
0!
#5950000
b1000111 &
1!
#5955000
0!
#5960000
b1001000 &
1!
#5965000
0!
#5970000
b1001001 &
1!
#5975000
0!
#5980000
b1001010 &
1!
#5985000
0!
#5990000
b1001011 &
1!
#5995000
0!
#6000000
b1001100 &
1!
#6005000
0!
#6010000
b1001101 &
1!
#6015000
0!
#6020000
b1001110 &
1!
#6025000
0!
#6030000
b1001111 &
1!
#6035000
0!
#6040000
b1010000 &
1!
#6045000
0!
#6050000
b1010001 &
1!
#6055000
0!
#6060000
b1010010 &
1!
#6065000
0!
#6070000
b1010011 &
1!
#6075000
0!
#6080000
b1010100 &
1!
#6085000
0!
#6090000
b1010101 &
1!
#6095000
0!
#6100000
b1010110 &
1!
#6105000
0!
#6110000
b1010111 &
1!
#6115000
0!
#6120000
b1011000 &
1!
#6125000
0!
#6130000
b1011001 &
1!
#6135000
0!
#6140000
b1011010 &
1!
#6145000
0!
#6150000
b1011011 &
1!
#6155000
0!
#6160000
b1011100 &
1!
#6165000
0!
#6170000
b1011101 &
1!
#6175000
0!
#6180000
b1011110 &
1!
#6185000
0!
#6190000
b1011111 &
1!
#6195000
0!
#6200000
b1100000 &
1!
#6205000
0!
#6210000
b1100001 &
1!
#6215000
0!
#6220000
b1100010 &
1!
#6225000
0!
#6230000
b1100011 &
1!
#6235000
0!
#6240000
b1100100 &
1!
#6245000
0!
#6250000
b1100101 &
1!
#6255000
0!
#6260000
b1100110 &
1!
#6265000
0!
#6270000
b1100111 &
1!
#6275000
0!
#6280000
b1101000 &
1!
#6285000
0!
#6290000
b1101001 &
1!
#6295000
0!
#6300000
b1101010 &
1!
#6305000
0!
#6310000
b1101011 &
1!
#6315000
0!
#6320000
b1101100 &
1!
#6325000
0!
#6330000
b1101101 &
1!
#6335000
0!
