src/pwm.v
`default_nettype none // do not optimize
`timescale 1ns/1ns // simulation 

module pwm (
    input wire clk,
    input wire reset,
    output wire out,
    input wire [7:0] level
    );

    reg [7:0] count;
    reg out_reg;
    localparam MAX_COUNT = 255; //8 bit

    always @(posedge clk) begin
        if(reset) 
        begin // reset active high
            count <= 8'b00000000;
            out_reg <= 1'b0;
        end
        else
        begin
            if(count == MAX_COUNT) 
            begin
                count <= 8'b00000000; // reset count when reached max
            end
            else 
            begin
                count <= count + 1'b1; // increment counter

                if((level == 8'b00000000) || (level == 8'b11111111)) begin
                     if (count < level) //minus 1 as out_reg is a register and will have update delay of 1 clock cycle
                        out_reg <= 1'b1;
                    else
                        out_reg <= 1'b0;
                end else begin
                    if (count < level-1'b1) //minus 1 as out_reg is a register and will have update delay of 1 clock cycle
                        out_reg <= 1'b1;
                    else
                        out_reg <= 1'b0;
                end
                
                
               
                // if (count < level-1'b1) //minus 1 as out_reg is a register and will have update delay of 1 clock cycle
                // if (count < level-1'b1) //minus 1 as out_reg is a register and will have update delay of 1 clock cycle
                //     out_reg <= 1'b1;
                // else
                //     out_reg <= 1'b0;
            end
        end
    end

    assign out = out_reg;

endmodule

src/encoder.v
`default_nettype none
`timescale 1ns/1ns

module encoder (
    input clk,
    input reset,
    input a,
    input b,
    output reg [7:0] value
);

//Signals here
wire [3:0] d_bus; //A,OA,B,OB
reg en;
reg OA, OB; //Previous clk input for A and B
reg [3:0] case_out; //inc 1, 2  dec 3, 4



always @(posedge clk) begin
    if(reset) begin
        // set output to 0
        value <= 0;
    end else begin
        //clock in data
        OA <= a;
        OB <= b;

        //case statement
        case(d_bus)
            //inc
            4'b1000: case_out = 4'b1000;
            4'b0111: case_out = 4'b0100;
            //dec
            4'b0010: case_out = 4'b0010;
            4'b1101: case_out = 4'b0001;

            default: case_out = 4'b0000;
        endcase

        // if(en) begin
        //     if ((case_out == 4'b1000) || (case_out == 4'b0100)) begin
        //         value <= value + 1'b1;
        //     end else if((case_out == 4'b0010) || (case_out == 4'b0001)) begin
        //         value <= value - 1'b1;
        //     end
        // end
        
        if(case_out != 4'b0000) begin
            en <= 1'b1;
        end else begin
            en <= 1'b0;
        end

        // if(en) begin
        //     if (case_out == 4'b1000) begin
        //         value <= value + 1'b1;
        //     end else if(case_out == 4'b0100) begin
        //         value <= value + 2'b10;
        //     end else if(case_out == 4'b0010) begin
        //         value <= value + 2'b11;
        //     end else if(case_out == 4'b0001) begin
        //         value <= value + 3'b100;
        //     end else
        //         value <= value + 3'b101;
        // end

        
        
            
        

    end
end

always @(posedge en) begin
    // if(en) begin
    //         if (case_out == 4'b1000) begin
    //             value <= value + 1'b1;
    //         end else if(case_out == 4'b0100) begin
    //             value <= value + 2'b10;
    //         end else if(case_out == 4'b0010) begin
    //             value <= value + 2'b11;
    //         end else if(case_out == 4'b0001) begin
    //             value <= value + 3'b100;
    //         end else
    //             value <= value + 3'b101;
    //     end
    if(en) begin
        if ((case_out == 4'b1000) || (case_out == 4'b0100)) begin
            value <= value + 1'b1;
        end else if((case_out == 4'b0010) || (case_out == 4'b0001)) begin
            value <= value - 1'b1;
        end
    end
end


assign d_bus[3] = a; 
assign d_bus[2] = OA; 
assign d_bus[1] = b; 
assign d_bus[0] = OB; 


endmodule

src/debounce.v
`default_nettype none
`timescale 1ns/1ns
module debounce (
    input wire clk,
    input wire reset,
    input wire button,
    output reg debounced
);

reg [7:0] shift_reg;
reg eq_FF, eq_00;
wire en;
wire D;

always @(posedge clk) begin
    if (reset) begin
        shift_reg <= 8'b00000000;
    end else begin
        shift_reg = (shift_reg << 1) | button;

        if (shift_reg == 8'b11111111) begin
            eq_FF <= 1'b1;
            eq_00 <= 1'b0;
        end else if (shift_reg == 8'b00000000)begin
            eq_FF <=1'b0;
            eq_00 <=1'b1;
        end
    end
    
end
assign en = eq_FF | eq_00;
assign D = eq_FF ? 1'b1 : 1'b0;


always @(posedge clk ) begin
    if(reset)begin
        debounced <= 1'b0;
    end else if(en == 1'b1) begin
        debounced <= D;
    end 
end

endmodule

src/rgb_mixer.v
`default_nettype none
`timescale 1ns/1ns
module rgb_mixer (
    input clk,
    input reset,
    input enc0_a,
    input enc0_b,
    input enc1_a,
    input enc1_b,
    input enc2_a,
    input enc2_b,
    output pwm0_out,
    output pwm1_out,
    output pwm2_out
);

//red
wire r_d_a, r_d_b;
wire [7:0] enc0;

//green
wire g_d_a, g_d_b;
wire [7:0] enc1;

//blue
wire b_d_a, b_d_b;
wire [7:0] enc2;


//red debounce
debounce red_debounce_a (clk, reset, enc0_a, r_d_a);
debounce red_debounce_b (clk, reset, enc0_b, r_d_b);

encoder red_encoder (clk, reset, r_d_a, r_d_b, enc0);

pwm red_pwm (clk, reset, pwm0_out, enc0);

//green debounce
debounce green_debounce_a (clk, reset, enc2_a, g_d_a);
debounce green_debounce_b (clk, reset, enc2_b, g_d_b);

encoder green_encoder (clk, reset, g_d_a, g_d_b, enc2);

pwm green_pwm (clk, reset, pwm2_out, enc2);

//blue debounce
debounce blue_debounce_a (clk, reset, enc1_a, b_d_a);
debounce blue_debounce_b (clk, reset, enc1_b, b_d_b);

encoder blue_encoder (clk, reset, b_d_a, b_d_b, enc1);

pwm blue_pwm (clk, reset, pwm1_out, enc1);


endmodule

rgb_mixer.vcd
$date
	Mon Jun 24 19:55:08 2024
$end
$version
	Icarus Verilog
$end
$timescale
	1ns
$end
$scope module rgb_mixer $end
$var wire 1 ! clk $end
$var wire 1 " enc0_a $end
$var wire 1 # enc0_b $end
$var wire 1 $ enc1_a $end
$var wire 1 % enc1_b $end
$var wire 1 & enc2_a $end
$var wire 1 ' enc2_b $end
$var wire 1 ( reset $end
$var wire 1 ) r_d_b $end
$var wire 1 * r_d_a $end
$var wire 1 + pwm2_out $end
$var wire 1 , pwm1_out $end
$var wire 1 - pwm0_out $end
$var wire 1 . g_d_b $end
$var wire 1 / g_d_a $end
$var wire 8 0 enc2 [7:0] $end
$var wire 8 1 enc1 [7:0] $end
$var wire 8 2 enc0 [7:0] $end
$var wire 1 3 b_d_b $end
$var wire 1 4 b_d_a $end
$scope module blue_debounce_a $end
$var wire 1 $ button $end
$var wire 1 ! clk $end
$var wire 1 5 en $end
$var wire 1 ( reset $end
$var wire 1 6 D $end
$var reg 1 4 debounced $end
$var reg 1 7 eq_00 $end
$var reg 1 8 eq_FF $end
$var reg 8 9 shift_reg [7:0] $end
$upscope $end
$scope module blue_debounce_b $end
$var wire 1 % button $end
$var wire 1 ! clk $end
$var wire 1 : en $end
$var wire 1 ( reset $end
$var wire 1 ; D $end
$var reg 1 3 debounced $end
$var reg 1 < eq_00 $end
$var reg 1 = eq_FF $end
$var reg 8 > shift_reg [7:0] $end
$upscope $end
$scope module blue_encoder $end
$var wire 1 4 a $end
$var wire 1 3 b $end
$var wire 1 ! clk $end
$var wire 1 ( reset $end
$var wire 4 ? d_bus [3:0] $end
$var reg 1 @ OA $end
$var reg 1 A OB $end
$var reg 4 B case_out [3:0] $end
$var reg 1 C en $end
$var reg 8 D value [7:0] $end
$upscope $end
$scope module blue_pwm $end
$var wire 1 ! clk $end
$var wire 8 E level [7:0] $end
$var wire 1 , out $end
$var wire 1 ( reset $end
$var parameter 32 F MAX_COUNT $end
$var reg 8 G count [7:0] $end
$var reg 1 H out_reg $end
$upscope $end
$scope module green_debounce_a $end
$var wire 1 & button $end
$var wire 1 ! clk $end
$var wire 1 I en $end
$var wire 1 ( reset $end
$var wire 1 J D $end
$var reg 1 / debounced $end
$var reg 1 K eq_00 $end
$var reg 1 L eq_FF $end
$var reg 8 M shift_reg [7:0] $end
$upscope $end
$scope module green_debounce_b $end
$var wire 1 ' button $end
$var wire 1 ! clk $end
$var wire 1 N en $end
$var wire 1 ( reset $end
$var wire 1 O D $end
$var reg 1 . debounced $end
$var reg 1 P eq_00 $end
$var reg 1 Q eq_FF $end
$var reg 8 R shift_reg [7:0] $end
$upscope $end
$scope module green_encoder $end
$var wire 1 / a $end
$var wire 1 . b $end
$var wire 1 ! clk $end
$var wire 1 ( reset $end
$var wire 4 S d_bus [3:0] $end
$var reg 1 T OA $end
$var reg 1 U OB $end
$var reg 4 V case_out [3:0] $end
$var reg 1 W en $end
$var reg 8 X value [7:0] $end
$upscope $end
$scope module green_pwm $end
$var wire 1 ! clk $end
$var wire 8 Y level [7:0] $end
$var wire 1 + out $end
$var wire 1 ( reset $end
$var parameter 32 Z MAX_COUNT $end
$var reg 8 [ count [7:0] $end
$var reg 1 \ out_reg $end
$upscope $end
$scope module red_debounce_a $end
$var wire 1 " button $end
$var wire 1 ! clk $end
$var wire 1 ] en $end
$var wire 1 ( reset $end
$var wire 1 ^ D $end
$var reg 1 * debounced $end
$var reg 1 _ eq_00 $end
$var reg 1 ` eq_FF $end
$var reg 8 a shift_reg [7:0] $end
$upscope $end
$scope module red_debounce_b $end
$var wire 1 # button $end
$var wire 1 ! clk $end
$var wire 1 b en $end
$var wire 1 ( reset $end
$var wire 1 c D $end
$var reg 1 ) debounced $end
$var reg 1 d eq_00 $end
$var reg 1 e eq_FF $end
$var reg 8 f shift_reg [7:0] $end
$upscope $end
$scope module red_encoder $end
$var wire 1 * a $end
$var wire 1 ) b $end
$var wire 1 ! clk $end
$var wire 1 ( reset $end
$var wire 4 g d_bus [3:0] $end
$var reg 1 h OA $end
$var reg 1 i OB $end
$var reg 4 j case_out [3:0] $end
$var reg 1 k en $end
$var reg 8 l value [7:0] $end
$upscope $end
$scope module red_pwm $end
$var wire 1 ! clk $end
$var wire 8 m level [7:0] $end
$var wire 1 - out $end
$var wire 1 ( reset $end
$var parameter 32 n MAX_COUNT $end
$var reg 8 o count [7:0] $end
$var reg 1 p out_reg $end
$upscope $end
$upscope $end
$enddefinitions $end
$comment Show the parameter values. $end
$dumpall
b11111111 n
b11111111 Z
b11111111 F
$end
#0
$dumpvars
0p
b0 o
b0 m
b0 l
xk
bx j
xi
xh
b0x0x g
b0 f
xe
xd
xc
xb
b0 a
x`
x_
x^
x]
0\
b0 [
b0 Y
b0 X
xW
bx V
xU
xT
b0x0x S
b0 R
xQ
xP
xO
xN
b0 M
xL
xK
xJ
xI
0H
b0 G
b0 E
b0 D
xC
bx B
xA
x@
b0x0x ?
b0 >
x=
x<
x;
x:
b0 9
x8
x7
x6
x5
04
03
b0 2
b0 1
b0 0
0/
0.
0-
0,
0+
0*
0)
1(
0'
0&
0%
0$
0#
0"
1!
$end
#5000
0!
#10000
1!
#15000
0!
#20000
1!
#25000
0!
#30000
1!
#35000
0!
#40000
0(
1!
#45000
0!
#50000
0;
1:
06
15
0O
1N
0J
1I
0c
1b
0^
1]
b1 G
0C
0A
b0 ?
0@
1<
0=
17
08
b1 [
0W
0U
b0 S
0T
1P
0Q
1K
0L
b1 o
0k
0i
b0 g
0h
1d
0e
1_
0`
b0 B
b0 V
b0 j
1!
#55000
0!
#60000
b10 o
b10 [
b10 G
1!
#65000
0!
#70000
b11 G
b11 [
b11 o
1!
#75000
0!
#80000
b100 o
b100 [
b100 G
1!
#85000
0!
#90000
b101 G
b101 [
b101 o
1!
#95000
0!
#100000
1#
b110 o
b110 [
b110 G
1!
#105000
0!
#110000
0#
b111 G
b111 [
b111 o
b1 f
1!
#115000
0!
#120000
b1000 o
b1000 [
b1000 G
b10 f
1!
#125000
0!
#130000
b1001 G
b1001 [
b1001 o
b100 f
1!
#135000
0!
#140000
b1010 o
b1010 [
b1010 G
b1000 f
1!
#145000
0!
#150000
b1011 G
b1011 [
b1011 o
b10000 f
1!
#155000
0!
#160000
b1100 o
b1100 [
b1100 G
b100000 f
1!
#165000
0!
#170000
b1101 G
b1101 [
b1101 o
b1000000 f
1!
#175000
0!
#180000
b1110 o
b1110 [
b1110 G
b10000000 f
1!
#185000
0!
#190000
b1111 G
b1111 [
b1111 o
b0 f
1!
#195000
0!
#200000
1"
b10000 o
b10000 [
b10000 G
1!
#205000
0!
#210000
0"
b10001 G
b10001 [
b10001 o
b1 a
1!
#215000
0!
#220000
1"
b10010 o
b10010 [
b10010 G
b10 a
1!
#225000
0!
#230000
b10011 G
b10011 [
b10011 o
b101 a
1!
#235000
0!
#240000
b10100 o
b10100 [
b10100 G
b1011 a
1!
#245000
0!
#250000
b10101 G
b10101 [
b10101 o
b10111 a
1!
#255000
0!
#260000
b10110 o
b10110 [
b10110 G
b101111 a
1!
#265000
0!
#270000
b10111 G
b10111 [
b10111 o
b1011111 a
1!
#275000
0!
#280000
b11000 o
b11000 [
b11000 G
b10111111 a
1!
#285000
0!
#290000
1#
b11001 G
b11001 [
b11001 o
b1111111 a
1!
#295000
0!
#300000
0#
1^
0_
1`
b11010 o
b11010 [
b11010 G
b11111111 a
b1 f
1!
#305000
0!
#310000
1#
b11011 G
b11011 [
b11011 o
b1000 g
1*
b10 f
1!
#315000
0!
#320000
b1 2
b1 l
b1 m
1k
b1100 g
1h
b11100 o
b11100 [
b11100 G
b101 f
b1000 j
1!
#325000
0!
#330000
b11101 G
b11101 [
b11101 o
0k
b0 j
b1011 f
1!
#335000
0!
#340000
b11110 o
b11110 [
b11110 G
b10111 f
1!
#345000
0!
#350000
b11111 G
b11111 [
b11111 o
b101111 f
1!
#355000
0!
#360000
b100000 o
b100000 [
b100000 G
b1011111 f
1!
#365000
0!
#370000
b100001 G
b100001 [
b100001 o
b10111111 f
1!
#375000
0!
#380000
b100010 o
b100010 [
b100010 G
b1111111 f
1!
#385000
0!
#390000
0"
1c
b100011 G
b100011 [
b100011 o
0d
1e
b11111111 f
1!
#395000
0!
#400000
1"
b1110 g
1)
b100100 o
b100100 [
b100100 G
b11111110 a
1!
#405000
0!
#410000
0"
b100101 G
b100101 [
b100101 o
b1111 g
1i
b11111101 a
1!
#415000
0!
#420000
b100110 o
b100110 [
b100110 G
b11111010 a
1!
#425000
0!
#430000
b100111 G
b100111 [
b100111 o
b11110100 a
1!
#435000
0!
#440000
b101000 o
b101000 [
b101000 G
b11101000 a
1!
#445000
0!
#450000
b101001 G
b101001 [
b101001 o
b11010000 a
1!
#455000
0!
#460000
b101010 o
b101010 [
b101010 G
b10100000 a
1!
#465000
0!
#470000
b101011 G
b101011 [
b101011 o
b1000000 a
1!
#475000
0!
#480000
b101100 o
b101100 [
b101100 G
b10000000 a
1!
#485000
0!
#490000
0#
0^
b101101 G
b101101 [
b101101 o
1_
0`
b0 a
1!
#495000
0!
#500000
b111 g
0*
b101110 o
b101110 [
b101110 G
b11111110 f
1!
#505000
0!
#510000
b10 2
b10 l
b10 m
b101111 G
b101111 [
b101111 o
1k
b11 g
0h
b100 j
b11111100 f
1!
#515000
0!
#520000
0k
b110000 o
b110000 [
b110000 G
b11111000 f
b0 j
1!
#525000
0!
#530000
b110001 G
b110001 [
b110001 o
b11110000 f
1!
#535000
0!
#540000
b110010 o
b110010 [
b110010 G
b11100000 f
1!
#545000
0!
#550000
b110011 G
b110011 [
b110011 o
b11000000 f
1!
#555000
0!
#560000
b110100 o
b110100 [
b110100 G
b10000000 f
1!
#565000
0!
#570000
0c
b110101 G
b110101 [
b110101 o
1d
0e
b0 f
1!
#575000
0!
#580000
b1 g
0)
b110110 o
b110110 [
b110110 G
1!
#585000
0!
#590000
1"
b110111 G
b110111 [
b110111 o
b0 g
0i
1!
#595000
0!
#600000
b111000 o
b111000 [
b111000 G
b1 a
1!
#605000
0!
#610000
b111001 G
b111001 [
b111001 o
b11 a
1!
#615000
0!
#620000
b111010 o
b111010 [
b111010 G
b111 a
1!
#625000
0!
#630000
b111011 G
b111011 [
b111011 o
b1111 a
1!
#635000
0!
#640000
b111100 o
b111100 [
b111100 G
b11111 a
1!
#645000
0!
#650000
b111101 G
b111101 [
b111101 o
b111111 a
1!
#655000
0!
#660000
b111110 o
b111110 [
b111110 G
b1111111 a
1!
#665000
0!
#670000
1^
b111111 G
b111111 [
b111111 o
0_
1`
b11111111 a
1!
#675000
0!
#680000
b1000 g
1*
b1000000 o
b1000000 [
b1000000 G
1!
#685000
0!
#690000
1#
b11 2
b11 l
b11 m
b1000001 G
b1000001 [
b1000001 o
1k
b1100 g
1h
b1000 j
1!
#695000
0!
#700000
0k
b1000010 o
b1000010 [
b1000010 G
b1 f
b0 j
1!
#705000
0!
#710000
b1000011 G
b1000011 [
b1000011 o
b11 f
1!
#715000
0!
#720000
b1000100 o
b1000100 [
b1000100 G
b111 f
1!
#725000
0!
#730000
b1000101 G
b1000101 [
b1000101 o
b1111 f
1!
#735000
0!
#740000
b1000110 o
b1000110 [
b1000110 G
b11111 f
1!
#745000
0!
#750000
b1000111 G
b1000111 [
b1000111 o
b111111 f
1!
#755000
0!
#760000
b1001000 o
b1001000 [
b1001000 G
b1111111 f
1!
#765000
0!
#770000
1c
b1001001 G
b1001001 [
b1001001 o
0d
1e
b11111111 f
1!
#775000
0!
#780000
b1110 g
1)
b1001010 o
b1001010 [
b1001010 G
1!
#785000
0!
#790000
0"
b1001011 G
b1001011 [
b1001011 o
b1111 g
1i
1!
#795000
0!
#800000
b1001100 o
b1001100 [
b1001100 G
b11111110 a
1!
#805000
0!
#810000
b1001101 G
b1001101 [
b1001101 o
b11111100 a
1!
#815000
0!
#820000
b1001110 o
b1001110 [
b1001110 G
b11111000 a
1!
#825000
0!
#830000
b1001111 G
b1001111 [
b1001111 o
b11110000 a
1!
#835000
0!
#840000
b1010000 o
b1010000 [
b1010000 G
b11100000 a
1!
#845000
0!
#850000
b1010001 G
b1010001 [
b1010001 o
b11000000 a
1!
#855000
0!
#860000
b1010010 o
b1010010 [
b1010010 G
b10000000 a
1!
#865000
0!
#870000
0^
b1010011 G
b1010011 [
b1010011 o
1_
0`
b0 a
1!
#875000
0!
#880000
b111 g
0*
b1010100 o
b1010100 [
b1010100 G
1!
#885000
0!
#890000
0#
b100 2
b100 l
b100 m
b1010101 G
b1010101 [
b1010101 o
1k
b11 g
0h
b100 j
1!
#895000
0!
#900000
0k
b1010110 o
b1010110 [
b1010110 G
b11111110 f
b0 j
1!
#905000
0!
#910000
b1010111 G
b1010111 [
b1010111 o
b11111100 f
1!
#915000
0!
#920000
b1011000 o
b1011000 [
b1011000 G
b11111000 f
1!
#925000
0!
#930000
b1011001 G
b1011001 [
b1011001 o
b11110000 f
1!
#935000
0!
#940000
b1011010 o
b1011010 [
b1011010 G
b11100000 f
1!
#945000
0!
#950000
b1011011 G
b1011011 [
b1011011 o
b11000000 f
1!
#955000
0!
#960000
b1011100 o
b1011100 [
b1011100 G
b10000000 f
1!
#965000
0!
#970000
0c
b1011101 G
b1011101 [
b1011101 o
1d
0e
b0 f
1!
#975000
0!
#980000
b1 g
0)
b1011110 o
b1011110 [
b1011110 G
1!
#985000
0!
#990000
1"
b1011111 G
b1011111 [
b1011111 o
b0 g
0i
1!
#995000
0!
#1000000
b1100000 o
b1100000 [
b1100000 G
b1 a
1!
#1005000
0!
#1010000
b1100001 G
b1100001 [
b1100001 o
b11 a
1!
#1015000
0!
#1020000
b1100010 o
b1100010 [
b1100010 G
b111 a
1!
#1025000
0!
#1030000
b1100011 G
b1100011 [
b1100011 o
b1111 a
1!
#1035000
0!
#1040000
b1100100 o
b1100100 [
b1100100 G
b11111 a
1!
#1045000
0!
#1050000
b1100101 G
b1100101 [
b1100101 o
b111111 a
1!
#1055000
0!
#1060000
b1100110 o
b1100110 [
b1100110 G
b1111111 a
1!
#1065000
0!
#1070000
1^
b1100111 G
b1100111 [
b1100111 o
0_
1`
b11111111 a
1!
#1075000
0!
#1080000
b1000 g
1*
b1101000 o
b1101000 [
b1101000 G
1!
#1085000
0!
#1090000
b101 2
b101 l
b101 m
b1101001 G
b1101001 [
b1101001 o
1k
b1100 g
1h
b1000 j
1!
#1095000
0!
#1100000
1#
0k
b1101010 o
b1101010 [
b1101010 G
b0 j
1!
#1105000
0!
#1110000
b1101011 G
b1101011 [
b1101011 o
b1 f
1!
#1115000
0!
#1120000
b1101100 o
b1101100 [
b1101100 G
b11 f
1!
#1125000
0!
#1130000
b1101101 G
b1101101 [
b1101101 o
b111 f
1!
#1135000
0!
#1140000
b1101110 o
b1101110 [
b1101110 G
b1111 f
1!
#1145000
0!
#1150000
b1101111 G
b1101111 [
b1101111 o
b11111 f
1!
#1155000
0!
#1160000
b1110000 o
b1110000 [
b1110000 G
b111111 f
1!
#1165000
0!
#1170000
b1110001 G
b1110001 [
b1110001 o
b1111111 f
1!
#1175000
0!
#1180000
1c
0d
1e
b1110010 o
b1110010 [
b1110010 G
b11111111 f
1!
#1185000
0!
#1190000
0"
b1110011 G
b1110011 [
b1110011 o
b1110 g
1)
1!
#1195000
0!
#1200000
b1111 g
1i
b1110100 o
b1110100 [
b1110100 G
b11111110 a
1!
#1205000
0!
#1210000
b1110101 G
b1110101 [
b1110101 o
b11111100 a
1!
#1215000
0!
#1220000
b1110110 o
b1110110 [
b1110110 G
b11111000 a
1!
#1225000
0!
#1230000
b1110111 G
b1110111 [
b1110111 o
b11110000 a
1!
#1235000
0!
#1240000
b1111000 o
b1111000 [
b1111000 G
b11100000 a
1!
#1245000
0!
#1250000
b1111001 G
b1111001 [
b1111001 o
b11000000 a
1!
#1255000
0!
#1260000
b1111010 o
b1111010 [
b1111010 G
b10000000 a
1!
#1265000
0!
#1270000
0^
b1111011 G
b1111011 [
b1111011 o
1_
0`
b0 a
1!
#1275000
0!
#1280000
b111 g
0*
b1111100 o
b1111100 [
b1111100 G
1!
#1285000
0!
#1290000
0#
b110 2
b110 l
b110 m
b1111101 G
b1111101 [
b1111101 o
1k
b11 g
0h
b100 j
1!
#1295000
0!
#1300000
0k
b1111110 o
b1111110 [
b1111110 G
b11111110 f
b0 j
1!
#1305000
0!
#1310000
b1111111 G
b1111111 [
b1111111 o
b11111100 f
1!
#1315000
0!
#1320000
b10000000 o
b10000000 [
b10000000 G
b11111000 f
1!
#1325000
0!
#1330000
b10000001 G
b10000001 [
b10000001 o
b11110000 f
1!
#1335000
0!
#1340000
b10000010 o
b10000010 [
b10000010 G
b11100000 f
1!
#1345000
0!
#1350000
b10000011 G
b10000011 [
b10000011 o
b11000000 f
1!
#1355000
0!
#1360000
b10000100 o
b10000100 [
b10000100 G
b10000000 f
1!
#1365000
0!
#1370000
0c
b10000101 G
b10000101 [
b10000101 o
1d
0e
b0 f
1!
#1375000
0!
#1380000
b1 g
0)
b10000110 o
b10000110 [
b10000110 G
1!
#1385000
0!
#1390000
1"
b10000111 G
b10000111 [
b10000111 o
b0 g
0i
1!
#1395000
0!
#1400000
b10001000 o
b10001000 [
b10001000 G
b1 a
1!
#1405000
0!
#1410000
0"
b10001001 G
b10001001 [
b10001001 o
b11 a
1!
#1415000
0!
#1420000
1"
b10001010 o
b10001010 [
b10001010 G
b110 a
1!
#1425000
0!
#1430000
b10001011 G
b10001011 [
b10001011 o
b1101 a
1!
#1435000
0!
#1440000
b10001100 o
b10001100 [
b10001100 G
b11011 a
1!
#1445000
0!
#1450000
b10001101 G
b10001101 [
b10001101 o
b110111 a
1!
#1455000
0!
#1460000
b10001110 o
b10001110 [
b10001110 G
b1101111 a
1!
#1465000
0!
#1470000
b10001111 G
b10001111 [
b10001111 o
b11011111 a
1!
#1475000
0!
#1480000
b10010000 o
b10010000 [
b10010000 G
b10111111 a
1!
#1485000
0!
#1490000
b10010001 G
b10010001 [
b10010001 o
b1111111 a
1!
#1495000
0!
#1500000
1^
0_
1`
b10010010 o
b10010010 [
b10010010 G
b11111111 a
1!
#1505000
0!
#1510000
1#
b10010011 G
b10010011 [
b10010011 o
b1000 g
1*
1!
#1515000
0!
#1520000
b111 2
b111 l
b111 m
1k
b1100 g
1h
b10010100 o
b10010100 [
b10010100 G
b1 f
b1000 j
1!
#1525000
0!
#1530000
b10010101 G
b10010101 [
b10010101 o
0k
b0 j
b11 f
1!
#1535000
0!
#1540000
b10010110 o
b10010110 [
b10010110 G
b111 f
1!
#1545000
0!
#1550000
b10010111 G
b10010111 [
b10010111 o
b1111 f
1!
#1555000
0!
#1560000
b10011000 o
b10011000 [
b10011000 G
b11111 f
1!
#1565000
0!
#1570000
b10011001 G
b10011001 [
b10011001 o
b111111 f
1!
#1575000
0!
#1580000
b10011010 o
b10011010 [
b10011010 G
b1111111 f
1!
#1585000
0!
#1590000
1c
b10011011 G
b10011011 [
b10011011 o
0d
1e
b11111111 f
1!
#1595000
0!
#1600000
0"
b1110 g
1)
b10011100 o
b10011100 [
b10011100 G
1!
#1605000
0!
#1610000
b10011101 G
b10011101 [
b10011101 o
b1111 g
1i
b11111110 a
1!
#1615000
0!
#1620000
b10011110 o
b10011110 [
b10011110 G
b11111100 a
1!
#1625000
0!
#1630000
b10011111 G
b10011111 [
b10011111 o
b11111000 a
1!
#1635000
0!
#1640000
b10100000 o
b10100000 [
b10100000 G
b11110000 a
1!
#1645000
0!
#1650000
b10100001 G
b10100001 [
b10100001 o
b11100000 a
1!
#1655000
0!
#1660000
b10100010 o
b10100010 [
b10100010 G
b11000000 a
1!
#1665000
0!
#1670000
b10100011 G
b10100011 [
b10100011 o
b10000000 a
1!
#1675000
0!
#1680000
0^
1_
0`
b10100100 o
b10100100 [
b10100100 G
b0 a
1!
#1685000
0!
#1690000
0#
b10100101 G
b10100101 [
b10100101 o
b111 g
0*
1!
#1695000
0!
#1700000
b1000 2
b1000 l
b1000 m
1k
b11 g
0h
b10100110 o
b10100110 [
b10100110 G
b11111110 f
b100 j
1!
#1705000
0!
#1710000
b10100111 G
b10100111 [
b10100111 o
0k
b0 j
b11111100 f
1!
#1715000
0!
#1720000
b10101000 o
b10101000 [
b10101000 G
b11111000 f
1!
#1725000
0!
#1730000
b10101001 G
b10101001 [
b10101001 o
b11110000 f
1!
#1735000
0!
#1740000
b10101010 o
b10101010 [
b10101010 G
b11100000 f
1!
#1745000
0!
#1750000
b10101011 G
b10101011 [
b10101011 o
b11000000 f
1!
#1755000
0!
#1760000
b10101100 o
b10101100 [
b10101100 G
b10000000 f
1!
#1765000
0!
#1770000
0c
b10101101 G
b10101101 [
b10101101 o
1d
0e
b0 f
1!
#1775000
0!
#1780000
b1 g
0)
b10101110 o
b10101110 [
b10101110 G
1!
#1785000
0!
#1790000
1"
b10101111 G
b10101111 [
b10101111 o
b0 g
0i
1!
#1795000
0!
#1800000
b10110000 o
b10110000 [
b10110000 G
b1 a
1!
#1805000
0!
#1810000
0"
b10110001 G
b10110001 [
b10110001 o
b11 a
1!
#1815000
0!
#1820000
1"
b10110010 o
b10110010 [
b10110010 G
b110 a
1!
#1825000
0!
#1830000
b10110011 G
b10110011 [
b10110011 o
b1101 a
1!
#1835000
0!
#1840000
b10110100 o
b10110100 [
b10110100 G
b11011 a
1!
#1845000
0!
#1850000
b10110101 G
b10110101 [
b10110101 o
b110111 a
1!
#1855000
0!
#1860000
b10110110 o
b10110110 [
b10110110 G
b1101111 a
1!
#1865000
0!
#1870000
b10110111 G
b10110111 [
b10110111 o
b11011111 a
1!
#1875000
0!
#1880000
b10111000 o
b10111000 [
b10111000 G
b10111111 a
1!
#1885000
0!
#1890000
1#
b10111001 G
b10111001 [
b10111001 o
b1111111 a
1!
#1895000
0!
#1900000
1^
0_
1`
b10111010 o
b10111010 [
b10111010 G
b11111111 a
b1 f
1!
#1905000
0!
#1910000
b10111011 G
b10111011 [
b10111011 o
b1000 g
1*
b11 f
1!
#1915000
0!
#1920000
b1001 2
b1001 l
b1001 m
1k
b1100 g
1h
b10111100 o
b10111100 [
b10111100 G
b111 f
b1000 j
1!
#1925000
0!
#1930000
b10111101 G
b10111101 [
b10111101 o
0k
b0 j
b1111 f
1!
#1935000
0!
#1940000
b10111110 o
b10111110 [
b10111110 G
b11111 f
1!
#1945000
0!
#1950000
b10111111 G
b10111111 [
b10111111 o
b111111 f
1!
#1955000
0!
#1960000
b11000000 o
b11000000 [
b11000000 G
b1111111 f
1!
#1965000
0!
#1970000
1c
b11000001 G
b11000001 [
b11000001 o
0d
1e
b11111111 f
1!
#1975000
0!
#1980000
b1110 g
1)
b11000010 o
b11000010 [
b11000010 G
1!
#1985000
0!
#1990000
0"
b11000011 G
b11000011 [
b11000011 o
b1111 g
1i
1!
#1995000
0!
#2000000
b11000100 o
b11000100 [
b11000100 G
b11111110 a
1!
#2005000
0!
#2010000
b11000101 G
b11000101 [
b11000101 o
b11111100 a
1!
#2015000
0!
#2020000
b11000110 o
b11000110 [
b11000110 G
b11111000 a
1!
#2025000
0!
#2030000
b11000111 G
b11000111 [
b11000111 o
b11110000 a
1!
#2035000
0!
#2040000
b11001000 o
b11001000 [
b11001000 G
b11100000 a
1!
#2045000
0!
#2050000
b11001001 G
b11001001 [
b11001001 o
b11000000 a
1!
#2055000
0!
#2060000
b11001010 o
b11001010 [
b11001010 G
b10000000 a
1!
#2065000
0!
#2070000
0^
b11001011 G
b11001011 [
b11001011 o
1_
0`
b0 a
1!
#2075000
0!
#2080000
b111 g
0*
b11001100 o
b11001100 [
b11001100 G
1!
#2085000
0!
#2090000
b1010 2
b1010 l
b1010 m
b11001101 G
b11001101 [
b11001101 o
1k
b11 g
0h
b100 j
1!
#2095000
0!
#2100000
0k
b11001110 o
b11001110 [
b11001110 G
b0 j
1!
#2105000
0!
#2110000
b11001111 G
b11001111 [
b11001111 o
1!
#2115000
0!
#2120000
0#
b11010000 o
b11010000 [
b11010000 G
1!
#2125000
0!
#2130000
b11010001 G
b11010001 [
b11010001 o
b11111110 f
1!
#2135000
0!
#2140000
b11010010 o
b11010010 [
b11010010 G
b11111100 f
1!
#2145000
0!
#2150000
b11010011 G
b11010011 [
b11010011 o
b11111000 f
1!
#2155000
0!
#2160000
b11010100 o
b11010100 [
b11010100 G
b11110000 f
1!
#2165000
0!
#2170000
b11010101 G
b11010101 [
b11010101 o
b11100000 f
1!
#2175000
0!
